Metadata-Version: 2.1
Name: spark-nlp-jsl-tmp
Version: 5.0.0
Summary: NLP Text processing library built on top of Apache Spark
Home-page: http://nlp.johnsnowlabs.com
Author: John Snow Labs
Author-email: john@johnsnowlabs.com
License: UNKNOWN
Keywords: NLP spark development
Platform: UNKNOWN
Classifier: Programming Language :: Python :: 3.6
